./.gitignore
./.python-version
./PKG-INFO
./README.md
./__init__.py
./pyproject.toml
./uv.lock
./weather.py
weather_didi-0.1.3.dist-info/METADATA
weather_didi-0.1.3.dist-info/WHEEL
weather_didi-0.1.3.dist-info/entry_points.txt
weather_didi-0.1.3.dist-info/RECORD
